{"nodes": [{"id": "home_db_space_apkallu_evals_agentic_test_isolation_sh", "label": "test_isolation.sh", "file_type": "code", "source_file": "evals/agentic/test_isolation.sh", "source_location": "L1", "metadata": {"language": "bash", "kind": "file"}}, {"id": "home_db_space_apkallu_evals_agentic_test_isolation_sh__entry", "label": "test_isolation.sh script", "file_type": "code", "source_file": "evals/agentic/test_isolation.sh", "source_location": "L1", "metadata": {"language": "bash", "kind": "bash_entrypoint"}}, {"id": "agentic_test_isolation_ok", "label": "ok()", "file_type": "code", "source_file": "evals/agentic/test_isolation.sh", "source_location": "L25", "metadata": {"language": "bash", "kind": "bash_function"}}, {"id": "agentic_test_isolation_bad", "label": "bad()", "file_type": "code", "source_file": "evals/agentic/test_isolation.sh", "source_location": "L26", "metadata": {"language": "bash", "kind": "bash_function"}}, {"id": "agentic_test_isolation_check", "label": "check()", "file_type": "code", "source_file": "evals/agentic/test_isolation.sh", "source_location": "L27", "metadata": {"language": "bash", "kind": "bash_function"}}, {"id": "agentic_test_isolation_ip_of", "label": "ip_of()", "file_type": "code", "source_file": "evals/agentic/test_isolation.sh", "source_location": "L29", "metadata": {"language": "bash", "kind": "bash_function"}}, {"id": "agentic_test_isolation_ssh_vm", "label": "ssh_vm()", "file_type": "code", "source_file": "evals/agentic/test_isolation.sh", "source_location": "L33", "metadata": {"language": "bash", "kind": "bash_function"}}, {"id": "agentic_test_isolation_http_code", "label": "http_code()", "file_type": "code", "source_file": "evals/agentic/test_isolation.sh", "source_location": "L38", "metadata": {"language": "bash", "kind": "bash_function"}}, {"id": "agentic_test_isolation_cleanup", "label": "cleanup()", "file_type": "code", "source_file": "evals/agentic/test_isolation.sh", "source_location": "L41", "metadata": {"language": "bash", "kind": "bash_function"}}, {"id": "agentic_test_isolation_is_rfc1918", "label": "is_rfc1918()", "file_type": "code", "source_file": "evals/agentic/test_isolation.sh", "source_location": "L48", "metadata": {"language": "bash", "kind": "bash_function"}}], "edges": [{"source": "home_db_space_apkallu_evals_agentic_test_isolation_sh", "target": "home_db_space_apkallu_evals_agentic_test_isolation_sh__entry", "relation": "contains", "confidence": "EXTRACTED", "source_file": "evals/agentic/test_isolation.sh", "source_location": "L1", "weight": 1.0}, {"source": "home_db_space_apkallu_evals_agentic_test_isolation_sh", "target": "agentic_test_isolation_ok", "relation": "defines", "confidence": "EXTRACTED", "source_file": "evals/agentic/test_isolation.sh", "source_location": "L25", "weight": 1.0}, {"source": "home_db_space_apkallu_evals_agentic_test_isolation_sh", "target": "agentic_test_isolation_bad", "relation": "defines", "confidence": "EXTRACTED", "source_file": "evals/agentic/test_isolation.sh", "source_location": "L26", "weight": 1.0}, {"source": "home_db_space_apkallu_evals_agentic_test_isolation_sh", "target": "agentic_test_isolation_check", "relation": "defines", "confidence": "EXTRACTED", "source_file": "evals/agentic/test_isolation.sh", "source_location": "L27", "weight": 1.0}, {"source": "home_db_space_apkallu_evals_agentic_test_isolation_sh", "target": "agentic_test_isolation_ip_of", "relation": "defines", "confidence": "EXTRACTED", "source_file": "evals/agentic/test_isolation.sh", "source_location": "L29", "weight": 1.0}, {"source": "home_db_space_apkallu_evals_agentic_test_isolation_sh", "target": "agentic_test_isolation_ssh_vm", "relation": "defines", "confidence": "EXTRACTED", "source_file": "evals/agentic/test_isolation.sh", "source_location": "L33", "weight": 1.0}, {"source": "home_db_space_apkallu_evals_agentic_test_isolation_sh", "target": "agentic_test_isolation_http_code", "relation": "defines", "confidence": "EXTRACTED", "source_file": "evals/agentic/test_isolation.sh", "source_location": "L38", "weight": 1.0}, {"source": "home_db_space_apkallu_evals_agentic_test_isolation_sh", "target": "agentic_test_isolation_cleanup", "relation": "defines", "confidence": "EXTRACTED", "source_file": "evals/agentic/test_isolation.sh", "source_location": "L41", "weight": 1.0}, {"source": "home_db_space_apkallu_evals_agentic_test_isolation_sh", "target": "agentic_test_isolation_is_rfc1918", "relation": "defines", "confidence": "EXTRACTED", "source_file": "evals/agentic/test_isolation.sh", "source_location": "L48", "weight": 1.0}, {"source": "home_db_space_apkallu_evals_agentic_test_isolation_sh__entry", "target": "agentic_test_isolation_check", "relation": "calls", "confidence": "EXTRACTED", "source_file": "evals/agentic/test_isolation.sh", "source_location": "L56", "weight": 1.0, "context": "call"}, {"source": "home_db_space_apkallu_evals_agentic_test_isolation_sh__entry", "target": "agentic_test_isolation_ok", "relation": "calls", "confidence": "EXTRACTED", "source_file": "evals/agentic/test_isolation.sh", "source_location": "L67", "weight": 1.0, "context": "call"}, {"source": "home_db_space_apkallu_evals_agentic_test_isolation_sh__entry", "target": "agentic_test_isolation_bad", "relation": "calls", "confidence": "EXTRACTED", "source_file": "evals/agentic/test_isolation.sh", "source_location": "L67", "weight": 1.0, "context": "call"}, {"source": "home_db_space_apkallu_evals_agentic_test_isolation_sh__entry", "target": "agentic_test_isolation_is_rfc1918", "relation": "calls", "confidence": "EXTRACTED", "source_file": "evals/agentic/test_isolation.sh", "source_location": "L69", "weight": 1.0, "context": "call"}, {"source": "home_db_space_apkallu_evals_agentic_test_isolation_sh__entry", "target": "agentic_test_isolation_ssh_vm", "relation": "calls", "confidence": "EXTRACTED", "source_file": "evals/agentic/test_isolation.sh", "source_location": "L95", "weight": 1.0, "context": "call"}, {"source": "agentic_test_isolation_check", "target": "agentic_test_isolation_ok", "relation": "calls", "confidence": "EXTRACTED", "source_file": "evals/agentic/test_isolation.sh", "source_location": "L27", "weight": 1.0, "context": "call"}, {"source": "agentic_test_isolation_check", "target": "agentic_test_isolation_bad", "relation": "calls", "confidence": "EXTRACTED", "source_file": "evals/agentic/test_isolation.sh", "source_location": "L27", "weight": 1.0, "context": "call"}, {"source": "agentic_test_isolation_http_code", "target": "agentic_test_isolation_ssh_vm", "relation": "calls", "confidence": "EXTRACTED", "source_file": "evals/agentic/test_isolation.sh", "source_location": "L38", "weight": 1.0, "context": "call"}]}